Ecomodulo/_init_.py
Ecomodulo/ecomodulo.py
ecomodulo-0.1.0.dist-info/licenses/LICENSE
ecomodulo-0.1.0.dist-info/METADATA
ecomodulo-0.1.0.dist-info/WHEEL
ecomodulo-0.1.0.dist-info/top_level.txt
ecomodulo-0.1.0.dist-info/RECORD
