Metadata-Version: 2.4
Name: ecomodulo
Version: 0.1.0
Summary: Librairie Python de formules économiques
Author-email: Muggy <muggy4216@gmail.com>
License-Expression: MIT
Requires-Python: >=3.7
License-File: LICENSE
Dynamic: license-file
